{
  "group_info": {
    "q_idx": 48,
    "item_id_range": "50-74",
    "matrix_shape": "(25, 25)"
  },
  "raw_scores_by_item": [
    {
      "item_id": 50,
      "bt_log_score": -3.31344246135293
    },
    {
      "item_id": 51,
      "bt_log_score": -7.28793000619342
    },
    {
      "item_id": 52,
      "bt_log_score": 5.889622999335884
    },
    {
      "item_id": 53,
      "bt_log_score": 6.502064257535248
    },
    {
      "item_id": 54,
      "bt_log_score": -5.4792299634639186
    },
    {
      "item_id": 55,
      "bt_log_score": -2.027949758372147
    },
    {
      "item_id": 56,
      "bt_log_score": -5.619744222098437
    },
    {
      "item_id": 57,
      "bt_log_score": -9.257517541332886
    },
    {
      "item_id": 58,
      "bt_log_score": -2.208774460048937
    },
    {
      "item_id": 59,
      "bt_log_score": -0.7271657456313239
    },
    {
      "item_id": 60,
      "bt_log_score": 2.252636460094458
    },
    {
      "item_id": 61,
      "bt_log_score": 8.646418283831927
    },
    {
      "item_id": 62,
      "bt_log_score": 9.538245839380119
    },
    {
      "item_id": 63,
      "bt_log_score": -0.9132468810396306
    },
    {
      "item_id": 64,
      "bt_log_score": -11.281814993966098
    },
    {
      "item_id": 65,
      "bt_log_score": -3.098080334567673
    },
    {
      "item_id": 66,
      "bt_log_score": 3.2156502699156393
    },
    {
      "item_id": 67,
      "bt_log_score": 7.043982829125778
    },
    {
      "item_id": 68,
      "bt_log_score": -7.049373749449944
    },
    {
      "item_id": 69,
      "bt_log_score": 0.6002330852341587
    },
    {
      "item_id": 70,
      "bt_log_score": 2.703282989517146
    },
    {
      "item_id": 71,
      "bt_log_score": -6.386814042497279
    },
    {
      "item_id": 72,
      "bt_log_score": 11.60772719400587
    },
    {
      "item_id": 73,
      "bt_log_score": 2.0437724209847365
    },
    {
      "item_id": 74,
      "bt_log_score": 4.607447531053661
    }
  ],
  "sorted_scores_by_method": {
    "Bradley-Terry (log)": [
      {
        "rank": 1,
        "item_id": 72,
        "score": 11.60772719400587
      },
      {
        "rank": 2,
        "item_id": 62,
        "score": 9.538245839380119
      },
      {
        "rank": 3,
        "item_id": 61,
        "score": 8.646418283831927
      },
      {
        "rank": 4,
        "item_id": 67,
        "score": 7.043982829125778
      },
      {
        "rank": 5,
        "item_id": 53,
        "score": 6.502064257535248
      },
      {
        "rank": 6,
        "item_id": 52,
        "score": 5.889622999335884
      },
      {
        "rank": 7,
        "item_id": 74,
        "score": 4.607447531053661
      },
      {
        "rank": 8,
        "item_id": 66,
        "score": 3.2156502699156393
      },
      {
        "rank": 9,
        "item_id": 70,
        "score": 2.703282989517146
      },
      {
        "rank": 10,
        "item_id": 60,
        "score": 2.252636460094458
      },
      {
        "rank": 11,
        "item_id": 73,
        "score": 2.0437724209847365
      },
      {
        "rank": 12,
        "item_id": 69,
        "score": 0.6002330852341587
      },
      {
        "rank": 13,
        "item_id": 59,
        "score": -0.7271657456313239
      },
      {
        "rank": 14,
        "item_id": 63,
        "score": -0.9132468810396306
      },
      {
        "rank": 15,
        "item_id": 55,
        "score": -2.027949758372147
      },
      {
        "rank": 16,
        "item_id": 58,
        "score": -2.208774460048937
      },
      {
        "rank": 17,
        "item_id": 65,
        "score": -3.098080334567673
      },
      {
        "rank": 18,
        "item_id": 50,
        "score": -3.31344246135293
      },
      {
        "rank": 19,
        "item_id": 54,
        "score": -5.4792299634639186
      },
      {
        "rank": 20,
        "item_id": 56,
        "score": -5.619744222098437
      },
      {
        "rank": 21,
        "item_id": 71,
        "score": -6.386814042497279
      },
      {
        "rank": 22,
        "item_id": 68,
        "score": -7.049373749449944
      },
      {
        "rank": 23,
        "item_id": 51,
        "score": -7.28793000619342
      },
      {
        "rank": 24,
        "item_id": 57,
        "score": -9.257517541332886
      },
      {
        "rank": 25,
        "item_id": 64,
        "score": -11.281814993966098
      }
    ]
  }
}