{
  "group_info": {
    "q_idx": 76,
    "item_id_range": "50-74",
    "matrix_shape": "(25, 25)"
  },
  "raw_scores_by_item": [
    {
      "item_id": 50,
      "bt_log_score": 0.3994681149244822
    },
    {
      "item_id": 51,
      "bt_log_score": -1.0844737351973988
    },
    {
      "item_id": 52,
      "bt_log_score": -0.6367938635409999
    },
    {
      "item_id": 53,
      "bt_log_score": 1.0275638278737522
    },
    {
      "item_id": 54,
      "bt_log_score": 0.9280560598323544
    },
    {
      "item_id": 55,
      "bt_log_score": 1.9796971021785277
    },
    {
      "item_id": 56,
      "bt_log_score": -5.762049000305385
    },
    {
      "item_id": 57,
      "bt_log_score": -0.3337398688261866
    },
    {
      "item_id": 58,
      "bt_log_score": 0.6891391358387425
    },
    {
      "item_id": 59,
      "bt_log_score": 3.7615533989611576
    },
    {
      "item_id": 60,
      "bt_log_score": 2.8435267338464105
    },
    {
      "item_id": 61,
      "bt_log_score": -4.342648250441426
    },
    {
      "item_id": 62,
      "bt_log_score": 1.2258866689957808
    },
    {
      "item_id": 63,
      "bt_log_score": -0.9667442521361305
    },
    {
      "item_id": 64,
      "bt_log_score": -8.63597404948269
    },
    {
      "item_id": 65,
      "bt_log_score": 2.541154079862037
    },
    {
      "item_id": 66,
      "bt_log_score": 0.5059923088085581
    },
    {
      "item_id": 67,
      "bt_log_score": 0.07820175706416915
    },
    {
      "item_id": 68,
      "bt_log_score": 2.1686160803066374
    },
    {
      "item_id": 69,
      "bt_log_score": 3.1192362137834633
    },
    {
      "item_id": 70,
      "bt_log_score": -4.308859261579446
    },
    {
      "item_id": 71,
      "bt_log_score": -1.3598741908564251
    },
    {
      "item_id": 72,
      "bt_log_score": 1.972995091174332
    },
    {
      "item_id": 73,
      "bt_log_score": 2.3241501769808424
    },
    {
      "item_id": 74,
      "bt_log_score": 1.8659197219348422
    }
  ],
  "sorted_scores_by_method": {
    "Bradley-Terry (log)": [
      {
        "rank": 1,
        "item_id": 59,
        "score": 3.7615533989611576
      },
      {
        "rank": 2,
        "item_id": 69,
        "score": 3.1192362137834633
      },
      {
        "rank": 3,
        "item_id": 60,
        "score": 2.8435267338464105
      },
      {
        "rank": 4,
        "item_id": 65,
        "score": 2.541154079862037
      },
      {
        "rank": 5,
        "item_id": 73,
        "score": 2.3241501769808424
      },
      {
        "rank": 6,
        "item_id": 68,
        "score": 2.1686160803066374
      },
      {
        "rank": 7,
        "item_id": 55,
        "score": 1.9796971021785277
      },
      {
        "rank": 8,
        "item_id": 72,
        "score": 1.972995091174332
      },
      {
        "rank": 9,
        "item_id": 74,
        "score": 1.8659197219348422
      },
      {
        "rank": 10,
        "item_id": 62,
        "score": 1.2258866689957808
      },
      {
        "rank": 11,
        "item_id": 53,
        "score": 1.0275638278737522
      },
      {
        "rank": 12,
        "item_id": 54,
        "score": 0.9280560598323544
      },
      {
        "rank": 13,
        "item_id": 58,
        "score": 0.6891391358387425
      },
      {
        "rank": 14,
        "item_id": 66,
        "score": 0.5059923088085581
      },
      {
        "rank": 15,
        "item_id": 50,
        "score": 0.3994681149244822
      },
      {
        "rank": 16,
        "item_id": 67,
        "score": 0.07820175706416915
      },
      {
        "rank": 17,
        "item_id": 57,
        "score": -0.3337398688261866
      },
      {
        "rank": 18,
        "item_id": 52,
        "score": -0.6367938635409999
      },
      {
        "rank": 19,
        "item_id": 63,
        "score": -0.9667442521361305
      },
      {
        "rank": 20,
        "item_id": 51,
        "score": -1.0844737351973988
      },
      {
        "rank": 21,
        "item_id": 71,
        "score": -1.3598741908564251
      },
      {
        "rank": 22,
        "item_id": 70,
        "score": -4.308859261579446
      },
      {
        "rank": 23,
        "item_id": 61,
        "score": -4.342648250441426
      },
      {
        "rank": 24,
        "item_id": 56,
        "score": -5.762049000305385
      },
      {
        "rank": 25,
        "item_id": 64,
        "score": -8.63597404948269
      }
    ]
  }
}