{
  "group_info": {
    "q_idx": 72,
    "item_id_range": "50-74",
    "matrix_shape": "(25, 25)"
  },
  "raw_scores_by_item": [
    {
      "item_id": 50,
      "bt_log_score": 0.41795402075631716
    },
    {
      "item_id": 51,
      "bt_log_score": -0.3356456235796523
    },
    {
      "item_id": 52,
      "bt_log_score": -2.62905385668024
    },
    {
      "item_id": 53,
      "bt_log_score": -1.3945617176992728
    },
    {
      "item_id": 54,
      "bt_log_score": 2.068990409234405
    },
    {
      "item_id": 55,
      "bt_log_score": 1.6167610529868883
    },
    {
      "item_id": 56,
      "bt_log_score": -1.0865973485979508
    },
    {
      "item_id": 57,
      "bt_log_score": -2.368574032119856
    },
    {
      "item_id": 58,
      "bt_log_score": -1.4482615685085962
    },
    {
      "item_id": 59,
      "bt_log_score": -1.0017334182862492
    },
    {
      "item_id": 60,
      "bt_log_score": -2.1831495543460457
    },
    {
      "item_id": 61,
      "bt_log_score": 0.12357096264621945
    },
    {
      "item_id": 62,
      "bt_log_score": 1.5536510399223307
    },
    {
      "item_id": 63,
      "bt_log_score": -1.0865973485979508
    },
    {
      "item_id": 64,
      "bt_log_score": 3.015598353665389
    },
    {
      "item_id": 65,
      "bt_log_score": -0.7089822213441744
    },
    {
      "item_id": 66,
      "bt_log_score": -0.11682288275349778
    },
    {
      "item_id": 67,
      "bt_log_score": 0.30786092270056836
    },
    {
      "item_id": 68,
      "bt_log_score": -1.1943395732959734
    },
    {
      "item_id": 69,
      "bt_log_score": 2.198041175056871
    },
    {
      "item_id": 70,
      "bt_log_score": -0.2334567240333182
    },
    {
      "item_id": 71,
      "bt_log_score": -1.394561717699273
    },
    {
      "item_id": 72,
      "bt_log_score": 3.8523791493396145
    },
    {
      "item_id": 73,
      "bt_log_score": 0.9117656537146286
    },
    {
      "item_id": 74,
      "bt_log_score": 1.1157648475188184
    }
  ],
  "sorted_scores_by_method": {
    "Bradley-Terry (log)": [
      {
        "rank": 1,
        "item_id": 72,
        "score": 3.8523791493396145
      },
      {
        "rank": 2,
        "item_id": 64,
        "score": 3.015598353665389
      },
      {
        "rank": 3,
        "item_id": 69,
        "score": 2.198041175056871
      },
      {
        "rank": 4,
        "item_id": 54,
        "score": 2.068990409234405
      },
      {
        "rank": 5,
        "item_id": 55,
        "score": 1.6167610529868883
      },
      {
        "rank": 6,
        "item_id": 62,
        "score": 1.5536510399223307
      },
      {
        "rank": 7,
        "item_id": 74,
        "score": 1.1157648475188184
      },
      {
        "rank": 8,
        "item_id": 73,
        "score": 0.9117656537146286
      },
      {
        "rank": 9,
        "item_id": 50,
        "score": 0.41795402075631716
      },
      {
        "rank": 10,
        "item_id": 67,
        "score": 0.30786092270056836
      },
      {
        "rank": 11,
        "item_id": 61,
        "score": 0.12357096264621945
      },
      {
        "rank": 12,
        "item_id": 66,
        "score": -0.11682288275349778
      },
      {
        "rank": 13,
        "item_id": 70,
        "score": -0.2334567240333182
      },
      {
        "rank": 14,
        "item_id": 51,
        "score": -0.3356456235796523
      },
      {
        "rank": 15,
        "item_id": 65,
        "score": -0.7089822213441744
      },
      {
        "rank": 16,
        "item_id": 59,
        "score": -1.0017334182862492
      },
      {
        "rank": 17,
        "item_id": 56,
        "score": -1.0865973485979508
      },
      {
        "rank": 18,
        "item_id": 63,
        "score": -1.0865973485979508
      },
      {
        "rank": 19,
        "item_id": 68,
        "score": -1.1943395732959734
      },
      {
        "rank": 20,
        "item_id": 53,
        "score": -1.3945617176992728
      },
      {
        "rank": 21,
        "item_id": 71,
        "score": -1.394561717699273
      },
      {
        "rank": 22,
        "item_id": 58,
        "score": -1.4482615685085962
      },
      {
        "rank": 23,
        "item_id": 60,
        "score": -2.1831495543460457
      },
      {
        "rank": 24,
        "item_id": 57,
        "score": -2.368574032119856
      },
      {
        "rank": 25,
        "item_id": 52,
        "score": -2.62905385668024
      }
    ]
  }
}