{
  "group_info": {
    "q_idx": 56,
    "item_id_range": "75-99",
    "matrix_shape": "(25, 25)"
  },
  "raw_scores_by_item": [
    {
      "item_id": 75,
      "bt_log_score": 1.1147374282859055
    },
    {
      "item_id": 76,
      "bt_log_score": 1.9064538343780328
    },
    {
      "item_id": 77,
      "bt_log_score": 1.6156358064032668
    },
    {
      "item_id": 78,
      "bt_log_score": -0.599487810513086
    },
    {
      "item_id": 79,
      "bt_log_score": 0.6659154444437928
    },
    {
      "item_id": 80,
      "bt_log_score": 1.673805420076476
    },
    {
      "item_id": 81,
      "bt_log_score": -2.6644740458976295
    },
    {
      "item_id": 82,
      "bt_log_score": -1.1755017316433016
    },
    {
      "item_id": 83,
      "bt_log_score": 0.17325959943246197
    },
    {
      "item_id": 84,
      "bt_log_score": 1.313002152770411
    },
    {
      "item_id": 85,
      "bt_log_score": 0.17325959943246197
    },
    {
      "item_id": 86,
      "bt_log_score": 1.7279670561399232
    },
    {
      "item_id": 87,
      "bt_log_score": -1.9419938663525989
    },
    {
      "item_id": 88,
      "bt_log_score": -3.4794123712073737
    },
    {
      "item_id": 89,
      "bt_log_score": 0.17325959943246197
    },
    {
      "item_id": 90,
      "bt_log_score": -2.7309743516509766
    },
    {
      "item_id": 91,
      "bt_log_score": -2.2218354595689993
    },
    {
      "item_id": 92,
      "bt_log_score": 0.9315441978389297
    },
    {
      "item_id": 93,
      "bt_log_score": 1.875405979795051
    },
    {
      "item_id": 94,
      "bt_log_score": 0.20412517642823658
    },
    {
      "item_id": 95,
      "bt_log_score": -0.8000139663114718
    },
    {
      "item_id": 96,
      "bt_log_score": 0.9978723555352628
    },
    {
      "item_id": 97,
      "bt_log_score": 1.6692904715552705
    },
    {
      "item_id": 98,
      "bt_log_score": -1.7183579339209152
    },
    {
      "item_id": 99,
      "bt_log_score": 1.1165174151184085
    }
  ],
  "sorted_scores_by_method": {
    "Bradley-Terry (log)": [
      {
        "rank": 1,
        "item_id": 76,
        "score": 1.9064538343780328
      },
      {
        "rank": 2,
        "item_id": 93,
        "score": 1.875405979795051
      },
      {
        "rank": 3,
        "item_id": 86,
        "score": 1.7279670561399232
      },
      {
        "rank": 4,
        "item_id": 80,
        "score": 1.673805420076476
      },
      {
        "rank": 5,
        "item_id": 97,
        "score": 1.6692904715552705
      },
      {
        "rank": 6,
        "item_id": 77,
        "score": 1.6156358064032668
      },
      {
        "rank": 7,
        "item_id": 84,
        "score": 1.313002152770411
      },
      {
        "rank": 8,
        "item_id": 99,
        "score": 1.1165174151184085
      },
      {
        "rank": 9,
        "item_id": 75,
        "score": 1.1147374282859055
      },
      {
        "rank": 10,
        "item_id": 96,
        "score": 0.9978723555352628
      },
      {
        "rank": 11,
        "item_id": 92,
        "score": 0.9315441978389297
      },
      {
        "rank": 12,
        "item_id": 79,
        "score": 0.6659154444437928
      },
      {
        "rank": 13,
        "item_id": 94,
        "score": 0.20412517642823658
      },
      {
        "rank": 14,
        "item_id": 83,
        "score": 0.17325959943246197
      },
      {
        "rank": 15,
        "item_id": 85,
        "score": 0.17325959943246197
      },
      {
        "rank": 16,
        "item_id": 89,
        "score": 0.17325959943246197
      },
      {
        "rank": 17,
        "item_id": 78,
        "score": -0.599487810513086
      },
      {
        "rank": 18,
        "item_id": 95,
        "score": -0.8000139663114718
      },
      {
        "rank": 19,
        "item_id": 82,
        "score": -1.1755017316433016
      },
      {
        "rank": 20,
        "item_id": 98,
        "score": -1.7183579339209152
      },
      {
        "rank": 21,
        "item_id": 87,
        "score": -1.9419938663525989
      },
      {
        "rank": 22,
        "item_id": 91,
        "score": -2.2218354595689993
      },
      {
        "rank": 23,
        "item_id": 81,
        "score": -2.6644740458976295
      },
      {
        "rank": 24,
        "item_id": 90,
        "score": -2.7309743516509766
      },
      {
        "rank": 25,
        "item_id": 88,
        "score": -3.4794123712073737
      }
    ]
  }
}